napari_error_reporter/__init__.py
napari_error_reporter/_opt_in_widget.py
napari_error_reporter/_util.py
napari_error_reporter/_version.py
napari_error_reporter/napari.yaml
napari_error_reporter-0.3.1.dist-info/LICENSE
napari_error_reporter-0.3.1.dist-info/METADATA
napari_error_reporter-0.3.1.dist-info/WHEEL
napari_error_reporter-0.3.1.dist-info/entry_points.txt
napari_error_reporter-0.3.1.dist-info/top_level.txt
napari_error_reporter-0.3.1.dist-info/RECORD
